pyqt_xarray_treeview-1.0.0.dist-info/METADATA
pyqt_xarray_treeview-1.0.0.dist-info/WHEEL
pyqt_xarray_treeview-1.0.0.dist-info/licenses/LICENSE
pyqt_xarray_treeview/PyQtXarrayTreeItem.py
pyqt_xarray_treeview/PyQtXarrayTreeModel.py
pyqt_xarray_treeview/PyQtXarrayTreeView.py
pyqt_xarray_treeview/__init__.py
pyqt_xarray_treeview/xarray_tree.py
pyqt_xarray_treeview-1.0.0.dist-info/RECORD
